python_state_manager/__init__.py
python_state_manager/state.py
python_state_manager/statemanager.py
python_state_manager-0.5.0.dist-info/LICENSE
python_state_manager-0.5.0.dist-info/METADATA
python_state_manager-0.5.0.dist-info/WHEEL
python_state_manager-0.5.0.dist-info/top_level.txt
python_state_manager-0.5.0.dist-info/RECORD
