Metadata-Version: 2.1
Name: python-state-manager
Version: 0.5.0
Summary: A simple state machine to handle states of programs.
Home-page: https://github.com/ChinmayShrivastava/pdf-page-annotator
Author: Chinmay Shrivastava
Author-email: cshrivastava99@gmail.com
License: GPLv3
Classifier: Development Status :: 3 - Alpha
Classifier: Intended Audience :: Developers
Classifier: License :: OSI Approved :: GNU General Public License v3 (GPLv3)
Classifier: Programming Language :: Python :: 3
Classifier: Environment :: MacOS X
Classifier: Environment :: Win32 (MS Windows)
Classifier: Environment :: X11 Applications
License-File: LICENSE
